{"dataURL":"file:\/\/\/Users\/omarkhattab\/Downloads\/BetterRest.csv","id":"FC46C203-7830-4E93-9C99-9C817522BF13","createdDate":"2022-08-03T15:49:20Z","title":"BetterRest.csv","modifiedDate":"2022-08-03T15:51:47Z","preferredFilename":"BetterRest.csv","version":"1.0","dataResult":{"dataURL":"file:\/\/\/Users\/omarkhattab\/Downloads\/BetterRest.csv","createdDate":"2022-08-03T15:49:20Z","dataSourceID":"FC46C203-7830-4E93-9C99-9C817522BF13"},"activityEntities":["dataSourceTrainingStarted",[{"id":"9F39AC1A-E52A-49C7-A29C-B107D6D7D896","title":"Used By","createdDate":"2022-08-03T15:51:47Z","event":"dataSourceTrainingStarted","subtitle":"BetterRestML 1"}],"dataSourceMetrics",[{"id":"26A75A39-4CB7-4A37-BBCB-ABAB76B716F2","title":"Data Summary","createdDate":"2022-08-03T15:51:47Z","event":"dataSourceMetrics","subtitle":"10,000 Items"}]],"pathType":0,"experimentIDs":["6BEC3396-EE9D-4D42-8371-74DFA6CE532D"]}